ptimeit/__init__.py
ptimeit/_impl.py
ptimeit-0.1.2.dist-info/LICENSE
ptimeit-0.1.2.dist-info/METADATA
ptimeit-0.1.2.dist-info/WHEEL
ptimeit-0.1.2.dist-info/top_level.txt
ptimeit-0.1.2.dist-info/RECORD
