Metadata-Version: 2.1
Name: ptimeit
Version: 0.1.2
Summary: Simple and pretty python code profiler for measuring execution time.
Home-page: https://github.com/narekgharibyan/ptimeit
Author: Narek Gharibyan
Author-email: narekgharibyan@gmail.com
License: UNKNOWN
Platform: UNKNOWN
Classifier: Programming Language :: Python :: 3
Classifier: License :: OSI Approved :: MIT License
Classifier: Operating System :: OS Independent
Requires-Python: >=3.6
License-File: LICENSE
